__init__.py
github_downloader.py
source_converter.py
source_converter-0.1.8.dist-info/METADATA
source_converter-0.1.8.dist-info/WHEEL
source_converter-0.1.8.dist-info/top_level.txt
source_converter-0.1.8.dist-info/RECORD
