Metadata-Version: 2.1
Name: source-converter
Version: 0.1.8
Summary: UNKNOWN
Home-page: UNKNOWN
License: UNKNOWN
Platform: UNKNOWN
Requires-Dist: pymovie (==3.6.6)
Requires-Dist: Pygments (==2.13.0)
Requires-Dist: pytest (==7.1.3)
Requires-Dist: requests (==2.28.1)
Requires-Dist: twine (==4.0.1)
